[
    {
        "season": "2025",
        "round": "1",
        "raceName": "Chinese Grand Prix",
        "Circuit": {
          "circuitId": "shanghai",
          "circuitName": "Shanghai International Circuit"
        },
        "Results": {
            "race1": [
                {
                    "number": "21",
                    "position": "1",
                    "grid": "4",
                    "laps": "13",
                    "status": "Finished",
                    "points": "10",
                    "Time": { "time": "32:24.230" },
                    "FastestLap": { "lap": "11", "Time": { "time": "2:04.874" } }
                },
                {
                    "number": "14",
                    "position": "2",
                    "grid": "5",
                    "laps": "13",
                    "status": "Finished",
                    "points": "8",
                    "Time": { "time": "32:24.436" },
                    "FastestLap": { "lap": "11", "Time": { "time": "2:04.580" } }
                },
                {
                    "number": "64",
                    "position": "3",
                    "grid": "8",
                    "laps": "13",
                    "status": "Finished",
                    "points": "6",
                    "Time": { "time": "32:25.546" },
                    "FastestLap": { "lap": "12", "Time": { "time": "2:04.909" } }
                },
                {
                    "number": "28",
                    "position": "4",
                    "grid": "7",
                    "laps": "13",
                    "status": "Finished",
                    "points": "5",
                    "Time": { "time": "32:29.669" },
                    "FastestLap": { "lap": "11", "Time": { "time": "2:05.489" } }
                },
                {
                    "number": "18",
                    "position": "5",
                    "grid": "13",
                    "laps": "13",
                    "status": "Finished",
                    "points": "4",
                    "Time": { "time": "32:33.800" },
                    "FastestLap": { "lap": "12", "Time": { "time": "2:06.234" } }
                },
                {
                    "number": "20",
                    "position": "6",
                    "grid": "11",
                    "laps": "13",
                    "status": "Finished",
                    "points": "3",
                    "Time": { "time": "32:35.138" },
                    "FastestLap": { "lap": "11", "Time": { "time": "2:05.872" } }
                },
                {
                    "number": "12",
                    "position": "7",
                    "grid": "6",
                    "laps": "13",
                    "status": "Finished",
                    "points": "2",
                    "Time": { "time": "32:39.123" },
                    "FastestLap": { "lap": "11", "Time": { "time": "2:05.153" } }
                },
                {
                    "number": "11",
                    "position": "8",
                    "grid": "16",
                    "laps": "13",
                    "status": "Finished",
                    "points": "1",
                    "Time": { "time": "32:40.351" },
                    "FastestLap": { "lap": "11", "Time": { "time": "2:06.651" } }
                },
                {
                    "number": "57",
                    "position": "9",
                    "grid": "N/A",
                    "laps": "13",
                    "status": "Finished",
                    "points": "0",
                    "Time": { "time": "32:48.190" },
                    "FastestLap": { "lap": "11", "Time": { "time": "2:05.970" } }
                },
                {
                    "number": "27",
                    "position": "10",
                    "grid": "10",
                    "laps": "13",
                    "status": "Finished",
                    "points": "0",
                    "Time": { "time": "32:49.244" },
                    "FastestLap": { "lap": "11", "Time": { "time": "2:07.580" } }
                },
                {
                    "number": "5",
                    "position": "11",
                    "grid": "2",
                    "laps": "13",
                    "status": "Finished",
                    "points": "0",
                    "Time": { "time": "33:06.514" },
                    "FastestLap": { "lap": "11", "Time": { "time": "2:05.483" } }
                },
                {
                    "number": "7",
                    "position": "12",
                    "grid": "15",
                    "laps": "13",
                    "status": "Finished",
                    "points": "0",
                    "Time": { "time": "33:08.057" },
                    "FastestLap": { "lap": "11", "Time": { "time": "2:06.933" } }
                },
                {
                    "number": "78",
                    "position": "13",
                    "grid": "9",
                    "laps": "13",
                    "status": "Finished",
                    "points": "0",
                    "Time": { "time": "33:14.843" },
                    "FastestLap": { "lap": "11", "Time": { "time": "2:05.639" } }
                },
                {
                    "number": "25",
                    "position": "14",
                    "grid": "3",
                    "laps": "13",
                    "status": "Finished",
                    "points": "0",
                    "Time": { "time": "34:03.313" },
                    "FastestLap": { "lap": "5", "Time": { "time": "2:10.702" } }
                },
                {
                    "number": "3",
                    "position": "15",
                    "grid": "1",
                    "laps": "12",
                    "status": "DNF",
                    "points": "0",
                    "Time": { "time": "" },
                    "FastestLap": { "lap": "11", "Time": { "time": "2:05.091" } }
                },
                {
                    "number": "2",
                    "position": "16",
                    "grid": "12",
                    "laps": "--",
                    "status": "DNF",
                    "points": "0",
                    "Time": { "time": "" },
                    "FastestLap": { "lap": "--", "Time": { "time": "--" } }
                },
                {
                    "number": "22",
                    "position": "17",
                    "grid": "14",
                    "laps": "--",
                    "status": "DNF",
                    "points": "0",
                    "Time": { "time": "" },
                    "FastestLap": { "lap": "--", "Time": { "time": "--" } }
                },
                {
                    "number": "24",
                    "position": "18",
                    "grid": "17",
                    "laps": "--",
                    "status": "DNF",
                    "points": "0",
                    "Time": { "time": "" },
                    "FastestLap": { "lap": "--", "Time": { "time": "--" } }
                }
            ],
            "race2": [
                {
                    "number": "28",
                    "position": "1",
                    "grid": "2",
                    "laps": "11",
                    "status": "Finished",
                    "points": "25",
                    "Time": { "time": "24:52.883" },
                    "FastestLap": { "lap": "6", "Time": { "time": "2:04.648" } }
                },
                {
                    "number": "64",
                    "position": "2",
                    "grid": "1",
                    "laps": "11",
                    "status": "Finished",
                    "points": "18",
                    "Time": { "time": "24:54.893" },
                    "FastestLap": { "lap": "7", "Time": { "time": "2:04.839" } }
                },
                {
                    "number": "14",
                    "position": "3",
                    "grid": "4",
                    "laps": "11",
                    "status": "Finished",
                    "points": "15",
                    "Time": { "time": "24:57.419" },
                    "FastestLap": { "lap": "7", "Time": { "time": "2:05.040" } }
                },
                {
                    "number": "12",
                    "position": "4",
                    "grid": "3",
                    "laps": "11",
                    "status": "Finished",
                    "points": "12",
                    "Time": { "time": "24:59.467" },
                    "FastestLap": { "lap": "7", "Time": { "time": "2:05.115" } }
                },
                {
                    "number": "5",
                    "position": "5",
                    "grid": "7",
                    "laps": "11",
                    "status": "Finished",
                    "points": "10",
                    "Time": { "time": "25:01.141" },
                    "FastestLap": { "lap": "7", "Time": { "time": "2:05.424" } }
                },
                {
                    "number": "21",
                    "position": "6",
                    "grid": "5",
                    "laps": "11",
                    "status": "Finished",
                    "points": "8",
                    "Time": { "time": "25:01.664" },
                    "FastestLap": { "lap": "7", "Time": { "time": "2:05.462" } }
                },
                {
                    "number": "20",
                    "position": "7",
                    "grid": "11",
                    "laps": "11",
                    "status": "Finished",
                    "points": "6",
                    "Time": { "time": "25:06.528" },
                    "FastestLap": { "lap": "7", "Time": { "time": "2:05.697" } }
                },
                {
                    "number": "18",
                    "position": "8",
                    "grid": "13",
                    "laps": "11",
                    "status": "Finished",
                    "points": "4",
                    "Time": { "time": "25:09.403" },
                    "FastestLap": { "lap": "7", "Time": { "time": "2:06.174" } }
                },
                {
                    "number": "57",
                    "position": "9",
                    "grid": "N/A",
                    "laps": "11",
                    "status": "Finished",
                    "points": "2",
                    "Time": { "time": "25:09.628" },
                    "FastestLap": { "lap": "7", "Time": { "time": "2:05.737" } }
                },
                {
                    "number": "3",
                    "position": "10",
                    "grid": "8",
                    "laps": "11",
                    "status": "Finished",
                    "points": "1",
                    "Time": { "time": "25:09.840" },
                    "FastestLap": { "lap": "7", "Time": { "time": "2:05.887" } }
                },
                {
                    "number": "27",
                    "position": "11",
                    "grid": "10",
                    "laps": "11",
                    "status": "Finished",
                    "points": "0",
                    "Time": { "time": "25:18.962" },
                    "FastestLap": { "lap": "7", "Time": { "time": "2:06.172" } }
                },
                {
                    "number": "7",
                    "position": "12",
                    "grid": "15",
                    "laps": "11",
                    "status": "Finished",
                    "points": "0",
                    "Time": { "time": "25:19.258" },
                    "FastestLap": { "lap": "7", "Time": { "time": "2:06.578" } }
                },
                {
                    "number": "11",
                    "position": "13",
                    "grid": "16",
                    "laps": "11",
                    "status": "Finished",
                    "points": "0",
                    "Time": { "time": "25:19.768" },
                    "FastestLap": { "lap": "6", "Time": { "time": "2:07.044" } }
                },
                {
                    "number": "24",
                    "position": "14",
                    "grid": "17",
                    "laps": "11",
                    "status": "Finished",
                    "points": "0",
                    "Time": { "time": "25:20.232" },
                    "FastestLap": { "lap": "7", "Time": { "time": "2:06.908" } }
                },
                {
                    "number": "78",
                    "position": "15",
                    "grid": "9",
                    "laps": "11",
                    "status": "Finished",
                    "points": "0",
                    "Time": { "time": "25:28.149" },
                    "FastestLap": { "lap": "6", "Time": { "time": "2:05.596" } }
                },
                {
                    "number": "2",
                    "position": "16",
                    "grid": "12",
                    "laps": "--",
                    "status": "DNF",
                    "points": "0",
                    "Time": { "time": "" },
                    "FastestLap": { "lap": "--", "Time": { "time": "--" } }
                },
                {
                    "number": "22",
                    "position": "17",
                    "grid": "14",
                    "laps": "--",
                    "status": "DNF",
                    "points": "0",
                    "Time": { "time": "" },
                    "FastestLap": { "lap": "--", "Time": { "time": "--" } }
                },
                {
                    "number": "25",
                    "position": "18",
                    "grid": "5",
                    "laps": "--",
                    "status": "DNF",
                    "points": "0",
                    "Time": { "time": "--" },
                    "FastestLap": { "lap": "--", "Time": { "time": "--" } }
                }
            ]
        }
    },
    {
        "season": "2025",
        "round": "2",
        "raceName": "Saudi Arabian Grand Prix",
        "Circuit": {
          "circuitId": "jeddah",
          "circuitName": "Jeddah Corniche Circuit"
        },
        "Results": {
            "race1": [
                {
                  "number": "20",
                  "position": "1",
                  "grid": "2",
                  "laps": "13",
                  "status": "Finished",
                  "points": "10",
                  "Time": {
                    "time": "30:00.870"
                  },
                  "FastestLap": {
                    "lap": "13",
                    "Time": {
                      "time": "2:05.663"
                    }
                  }
                },
                {
                  "number": "64",
                  "position": "2",
                  "grid": "6",
                  "laps": "13",
                  "status": "Finished",
                  "points": "8",
                  "Time": {
                    "time": "30:01.046"
                  },
                  "FastestLap": {
                    "lap": "13",
                    "Time": {
                      "time": "2:05.226"
                    }
                  }
                },
                {
                  "number": "21",
                  "position": "3",
                  "grid": "5",
                  "laps": "9",
                  "status": "Finished",
                  "points": "6",
                  "Time": {
                    "time": "30:02.693"
                  },
                  "FastestLap": {
                    "lap": "9",
                    "Time": {
                      "time": "2:05.908"
                    }
                  }
                },
                {
                  "number": "28",
                  "position": "4",
                  "grid": "7",
                  "laps": "11",
                  "status": "Finished",
                  "points": "6",
                  "Time": {
                    "time": "30:02.919"
                  },
                  "FastestLap": {
                    "lap": "11",
                    "Time": {
                      "time": "2:05.225"
                    }
                  }
                },
                {
                  "number": "12",
                  "position": "5",
                  "grid": "4",
                  "laps": "13",
                  "status": "Finished",
                  "points": "4",
                  "Time": {
                    "time": "30:04.222"
                  },
                  "FastestLap": {
                    "lap": "13",
                    "Time": {
                      "time": "2:05.363"
                    }
                  }
                },
                {
                  "number": "78",
                  "position": "6",
                  "grid": "3",
                  "laps": "11",
                  "status": "Finished",
                  "points": "3",
                  "Time": {
                    "time": "30:06.028"
                  },
                  "FastestLap": {
                    "lap": "11",
                    "Time": {
                      "time": "2:05.849"
                    }
                  }
                },
                {
                  "number": "14",
                  "position": "7",
                  "grid": "8",
                  "laps": "13",
                  "status": "Finished",
                  "points": "2",
                  "Time": {
                    "time": "30:06.513"
                  },
                  "FastestLap": {
                    "lap": "13",
                    "Time": {
                      "time": "2:05.748"
                    }
                  }
                },
                {
                  "number": "3",
                  "position": "8",
                  "grid": "9",
                  "laps": "12",
                  "status": "Finished",
                  "points": "1",
                  "Time": {
                    "time": "30:10.207"
                  },
                  "FastestLap": {
                    "lap": "12",
                    "Time": {
                      "time": "2:06.110"
                    }
                  }
                },
                {
                  "number": "5",
                  "position": "9",
                  "grid": "1",
                  "laps": "13",
                  "status": "Finished",
                  "points": "0",
                  "Time": {
                    "time": "30:11.464"
                  },
                  "FastestLap": {
                    "lap": "13",
                    "Time": {
                      "time": "2:06.301"
                    }
                  }
                },
                {
                  "number": "22",
                  "position": "10",
                  "grid": "12",
                  "laps": "12",
                  "status": "Finished",
                  "points": "0",
                  "Time": {
                    "time": "30:12.266"
                  },
                  "FastestLap": {
                    "lap": "12",
                    "Time": {
                      "time": "2:06.539"
                    }
                  }
                },
                {
                  "number": "25",
                  "position": "11",
                  "grid": "11",
                  "laps": "13",
                  "status": "Finished",
                  "points": "0",
                  "Time": {
                    "time": "30:13.520"
                  },
                  "FastestLap": {
                    "lap": "13",
                    "Time": {
                      "time": "2:05.872"
                    }
                  }
                },
                {
                  "number": "57",
                  "position": "12",
                  "grid": "N/A",
                  "laps": "13",
                  "status": "Finished",
                  "points": "0",
                  "Time": {
                    "time": "30:16.518"
                  },
                  "FastestLap": {
                    "lap": "13",
                    "Time": {
                      "time": "2:06.446"
                    }
                  }
                },
                {
                  "number": "18",
                  "position": "13",
                  "grid": "13",
                  "laps": "13",
                  "status": "Finished",
                  "points": "0",
                  "Time": {
                    "time": "30:17.253"
                  },
                  "FastestLap": {
                    "lap": "13",
                    "Time": {
                      "time": "2:06.991"
                    }
                  }
                },
                {
                  "number": "11",
                  "position": "14",
                  "grid": "16",
                  "laps": "10",
                  "status": "Finished",
                  "points": "0",
                  "Time": {
                    "time": "30:21.706"
                  },
                  "FastestLap": {
                    "lap": "10",
                    "Time": {
                      "time": "2:08.089"
                    }
                  }
                },
                {
                  "number": "2",
                  "position": "15",
                  "grid": "15",
                  "laps": "11",
                  "status": "Finished",
                  "points": "0",
                  "Time": {
                    "time": "30:26.600"
                  },
                  "FastestLap": {
                    "lap": "11",
                    "Time": {
                      "time": "2:07.398"
                    }
                  }
                },
                {
                  "number": "4",
                  "position": "16",
                  "grid": "17",
                  "laps": "13",
                  "status": "Finished",
                  "points": "0",
                  "Time": {
                    "time": "31:38.880"
                  },
                  "FastestLap": {
                    "lap": "13",
                    "Time": {
                      "time": "2:11.944"
                    }
                  }
                }
              ],
            "race2": [
                {
                  "number": "64",
                  "position": "1",
                  "grid": "3",
                  "laps": "10",
                  "status": "Finished",
                  "Time": {
                    "time": "27:18.850"
                  },
                  "FastestLap": {
                    "lap": "10",
                    "Time": {
                      "time": "2:05.006"
                    }
                  }
                },
                {
                  "number": "14",
                  "position": "2",
                  "grid": "1",
                  "laps": "13",
                  "status": "Finished",
                  "Time": {
                    "time": "27:21.634"
                  },
                  "FastestLap": {
                    "lap": "13",
                    "Time": {
                      "time": "2:04.922"
                    }
                  }
                },
                {
                  "number": "28",
                  "position": "3",
                  "grid": "2",
                  "laps": "9",
                  "status": "Finished",
                  "points": "15",
                  "Time": {
                    "time": "27:21.699"
                  },
                  "FastestLap": {
                    "lap": "9",
                    "Time": {
                      "time": "2:05.367"
                    }
                  }
                },
                {
                  "number": "21",
                  "position": "4",
                  "grid": "4",
                  "laps": "11",
                  "status": "Finished",
                  "points": "12",
                  "Time": {
                    "time": "27:22.732"
                  },
                  "FastestLap": {
                    "lap": "11",
                    "Time": {
                      "time": "2:05.365"
                    }
                  }
                },
                {
                  "number": "12",
                  "position": "5",
                  "grid": "5",
                  "laps": "12",
                  "status": "Finished",
                  "points": "10",
                  "Time": {
                    "time": "27:23.219"
                  },
                  "FastestLap": {
                    "lap": "12",
                    "Time": {
                      "time": "2:05.341"
                    }
                  }
                },
                {
                  "number": "78",
                  "position": "6",
                  "grid": "6",
                  "laps": "11",
                  "status": "Finished",
                  "points": "8",
                  "Time": {
                    "time": "27:27.217"
                  },
                  "FastestLap": {
                    "lap": "11",
                    "Time": {
                      "time": "2:05.811"
                    }
                  }
                },
                {
                  "number": "3",
                  "position": "7",
                  "grid": "9",
                  "laps": "9",
                  "status": "Finished",
                  "points": "6",
                  "Time": {
                    "time": "27:32.992"
                  },
                  "FastestLap": {
                    "lap": "9",
                    "Time": {
                      "time": "2:05.932"
                    }
                  }
                },
                {
                  "number": "20",
                  "position": "8",
                  "grid": "7",
                  "laps": "11",
                  "status": "Finished",
                  "points": "4",
                  "Time": {
                    "time": "27:37.835"
                  },
                  "FastestLap": {
                    "lap": "11",
                    "Time": {
                      "time": "2:06.218"
                    }
                  }
                },
                {
                  "number": "25",
                  "position": "9",
                  "grid": "11",
                  "laps": "13",
                  "status": "Finished",
                  "points": "2",
                  "Time": {
                    "time": "27:40.470"
                  },
                  "FastestLap": {
                    "lap": "13",
                    "Time": {
                      "time": "2:06.253"
                    }
                  }
                },
                {
                  "number": "27",
                  "position": "10",
                  "grid": "10",
                  "laps": "9",
                  "status": "Finished",
                  "points": "1",
                  "Time": {
                    "time": "27:42.209"
                  },
                  "FastestLap": {
                    "lap": "9",
                    "Time": {
                      "time": "2:06.321"
                    }
                  }
                },
                {
                  "number": "22",
                  "position": "11",
                  "grid": "12",
                  "laps": "13",
                  "status": "Finished",
                  "points": "0",
                  "Time": {
                    "time": "27:43.239"
                  },
                  "FastestLap": {
                    "lap": "13",
                    "Time": {
                      "time": "2:06.173"
                    }
                  }
                },
                {
                  "number": "7",
                  "position": "12",
                  "grid": "14",
                  "laps": "9",
                  "status": "Finished",
                  "points": "0",
                  "Time": {
                    "time": "27:45.848"
                  },
                  "FastestLap": {
                    "lap": "9",
                    "Time": {
                      "time": "2:06.712"
                    }
                  }
                },
                {
                  "number": "18",
                  "position": "13",
                  "grid": "13",
                  "laps": "12",
                  "status": "Finished",
                  "points": "0",
                  "Time": {
                    "time": "27:45.955"
                  },
                  "FastestLap": {
                    "lap": "12",
                    "Time": {
                      "time": "2:06.247"
                    }
                  }
                },
                {
                  "number": "57",
                  "position": "14",
                  "grid": "N/A",
                  "laps": "13",
                  "status": "Finished",
                  "points": "0",
                  "Time": {
                    "time": "27:46.101"
                  },
                  "FastestLap": {
                    "lap": "13",
                    "Time": {
                      "time": "2:06.439"
                    }
                  }
                },
                {
                  "number": "5",
                  "position": "15",
                  "grid": "8",
                  "laps": "13",
                  "status": "Finished",
                  "points": "0",
                  "Time": {
                    "time": "27:51.616"
                  },
                  "FastestLap": {
                    "lap": "13",
                    "Time": {
                      "time": "2:06.035"
                    }
                  }
                },
                {
                  "number": "2",
                  "position": "16",
                  "grid": "15",
                  "laps": "12",
                  "status": "Finished",
                  "points": "0",
                  "Time": {
                    "time": "27:54.434"
                  },
                  "FastestLap": {
                    "lap": "12",
                    "Time": {
                      "time": "2:06.764"
                    }
                  }
                },
                {
                  "number": "11",
                  "position": "17",
                  "grid": "16",
                  "laps": "13",
                  "status": "Finished",
                  "points": "0",
                  "Time": {
                    "time": "27:57.363"
                  },
                  "FastestLap": {
                    "lap": "13",
                    "Time": {
                      "time": "2:07.216"
                    }
                  }
                },
                {
                  "number": "4",
                  "position": "18",
                  "grid": "17",
                  "laps": "10",
                  "status": "Finished",
                  "points": "0",
                  "Time": {
                    "time": "29:00.258"
                  },
                  "FastestLap": {
                    "lap": "10",
                    "Time": {
                      "time": "2:11.823"
                    }
                  }
                }
              ]
        }
    },
    {
        "season": "2025",
        "round": "2",
        "raceName": "Miami Grand Prix",
        "Circuit": {
            "circuitId": "miami",
            "circuitName": "Miami Grand Prix"
        },
        "Results": {
            "race1": [
              {
                "number": "28",
                "position": "1",
                "grid": "6",
                "laps": "13",
                "status": "Finished",
                "points": "11",
                "Time": { "time": "28:32.874" },
                "FastestLap": { "lap": "11", "Time": { "time": "1:59.386" } }
              },
              {
                "number": "21",
                "position": "2",
                "grid": "7",
                "laps": "13",
                "status": "Finished",
                "points": "8",
                "Time": { "time": "28:33.297" },
                "FastestLap": { "lap": "12", "Time": { "time": "1:59.490" } }
              },
              {
                "number": "14",
                "position": "3",
                "grid": "8",
                "laps": "13",
                "status": "Finished",
                "points": "6",
                "Time": { "time": "28:34.613" },
                "FastestLap": { "lap": "3", "Time": { "time": "1:59.576" } }
              },
              {
                "number": "64",
                "position": "4",
                "grid": "10",
                "laps": "13",
                "status": "Finished",
                "points": "5",
                "Time": { "time": "28:35.539" },
                "FastestLap": { "lap": "13", "Time": { "time": "1:59.496" } }
              },
              {
                "number": "3",
                "position": "5",
                "grid": "13",
                "laps": "13",
                "status": "Finished",
                "points": "4",
                "Time": { "time": "28:39.037" },
                "FastestLap": { "lap": "12", "Time": { "time": "1:59.974" } }
              },
              {
                "number": "22",
                "position": "6",
                "grid": "3",
                "laps": "13",
                "status": "Finished",
                "points": "3",
                "Time": { "time": "28:39.565" },
                "FastestLap": { "lap": "3", "Time": { "time": "2:00.075" } }
              },
              {
                "number": "78",
                "position": "7",
                "grid": "9",
                "laps": "13",
                "status": "Finished",
                "points": "2",
                "Time": { "time": "28:39.662" },
                "FastestLap": { "lap": "3", "Time": { "time": "2:00.474" } }
              },
              {
                "number": "18",
                "position": "8",
                "grid": "2",
                "laps": "13",
                "status": "Finished",
                "points": "1",
                "Time": { "time": "28:40.643" },
                "FastestLap": { "lap": "5", "Time": { "time": "2:00.488" } }
              },
              {
                "number": "7",
                "position": "9",
                "grid": "11",
                "laps": "13",
                "status": "Finished",
                "points": "0",
                "Time": { "time": "28:42.824" },
                "FastestLap": { "lap": "13", "Time": { "time": "2:00.397" } }
              },
              {
                "number": "57",
                "position": "10",
                "grid": "4",
                "laps": "13",
                "status": "Finished",
                "points": "0",
                "Time": { "time": "28:43.416" },
                "FastestLap": { "lap": "6", "Time": { "time": "1:59.826" } }
              },
              {
                "number": "12",
                "position": "11",
                "grid": "12",
                "laps": "13",
                "status": "Finished",
                "points": "0",
                "Time": { "time": "28:46.840" },
                "FastestLap": { "lap": "4", "Time": { "time": "2:00.446" } }
              },
              {
                "number": "2",
                "position": "12",
                "grid": "15",
                "laps": "13",
                "status": "Finished",
                "points": "0",
                "Time": { "time": "28:47.369" },
                "FastestLap": { "lap": "4", "Time": { "time": "2:01.631" } }
              },
              {
                "number": "90",
                "position": "13",
                "grid": "18",
                "laps": "13",
                "status": "Finished",
                "points": "0",
                "Time": { "time": "28:47.830" },
                "FastestLap": { "lap": "6", "Time": { "time": "2:01.328" } }
              },
              {
                "number": "11",
                "position": "14",
                "grid": "17",
                "laps": "13",
                "status": "Finished",
                "points": "0",
                "Time": { "time": "28:48.983" },
                "FastestLap": { "lap": "4", "Time": { "time": "2:01.656" } }
              },
              {
                "number": "5",
                "position": "15",
                "grid": "1",
                "laps": "13",
                "status": "Finished",
                "points": "0",
                "Time": { "time": "28:52.877" },
                "FastestLap": { "lap": "6", "Time": { "time": "2:00.682" } }
              },
              {
                "number": "25",
                "position": "",
                "grid": "16",
                "laps": "",
                "status": "DNF",
                "points": "0",
                "Time": { "time": "" },
                "FastestLap": { "lap": "", "Time": { "time": "" } }
              },
              {
                "number": "27",
                "position": "",
                "grid": "14",
                "laps": "",
                "status": "DNF",
                "points": "0",
                "Time": { "time": "" },
                "FastestLap": { "lap": "", "Time": { "time": "" } }
              },
              {
                "number": "20",
                "position": "",
                "grid": "5",
                "laps": "",
                "status": "DNF",
                "points": "0",
                "Time": { "time": "" },
                "FastestLap": { "lap": "", "Time": { "time": "" } }
              }
              ]
        }
    }
]